{
    "$schema": "some_schema_file_path",
    "category": "Productivity",
    "createdby": "jopemachine",
    "description": "App launcher plugin for Arvis",
    "defaultIcon": "icon.png",
    "name": "arvis-app-launcher-plugin",
    "readme": "https://github.com/jopemachine/arvis-app-launcher-plugin",
    "version": "0.0.1",
    "webaddress": "https://github.com/jopemachine/arvis-app-launcher-plugin",
    "enabled": true,
    "main": "index.js",
    "action": [
        {
            "modifiers": "normal",
            "type": "script",
            "script": "node open.js '{query}'"
        }
    ]
}
